uninas/__init__.py
uninas/model.py
uninas/nodes.py
uninas/nodes/__init__.py
uninas/nodes/base.py
uninas/nodes/batchnorm.py
uninas/nodes/conv1.py
uninas/nodes/conv3.py
uninas/nodes/convdepth3.py
uninas/nodes/convdepth5.py
uninas/nodes/dropout.py
uninas/nodes/gelu.py
uninas/nodes/identity.py
uninas/nodes/layernorm.py
uninas/nodes/mask.py
uninas/nodes/maxpool.py
uninas/nodes/relposbias.py
uninas/nodes/sigmoid.py
uninas/nodes/softmax.py
uninas/nodes/special.py
uninas/nodes/utils.py
uninas/nodes/zero.py
uninas-0.0.2.dist-info/METADATA
uninas-0.0.2.dist-info/WHEEL
uninas-0.0.2.dist-info/top_level.txt
uninas-0.0.2.dist-info/RECORD
