Metadata-Version: 2.4
Name: uninas
Version: 0.0.2
Summary: string_to_model
Author-email: Ondrej Tybl <ondra@tybl.cz>
Requires-Python: >=3.11
Requires-Dist: torch>=2.9.1
Requires-Dist: timm>=1.0.24
